panoply/__init__.py
panoply/constants.py
panoply/datasource.py
panoply/errors.py
panoply/events.py
panoply/sdk.py
panoply_python_sdk-1.6.1.dist-info/LICENSE
panoply_python_sdk-1.6.1.dist-info/METADATA
panoply_python_sdk-1.6.1.dist-info/WHEEL
panoply_python_sdk-1.6.1.dist-info/top_level.txt
panoply_python_sdk-1.6.1.dist-info/RECORD
